ps_dia_modules/__init__.py
ps_dia_modules/slacker.py
ps_dia_modules-0.0.31.dist-info/LICENSE.txt
ps_dia_modules-0.0.31.dist-info/METADATA
ps_dia_modules-0.0.31.dist-info/WHEEL
ps_dia_modules-0.0.31.dist-info/top_level.txt
ps_dia_modules-0.0.31.dist-info/RECORD
