Metadata-Version: 2.1
Name: ps-dia-modules
Version: 0.0.31
Summary: Data Analytics Architecture Automation
Home-page: https://gitlab.com/pluralsight/ps-data-team/_modules
Author: Matthew Skinner
Author-email: matthew-skinner@pluralsight.com
License: UNKNOWN
Project-URL: Bug Tracker, https://gitlab.com/pluralsight/ps-data-team/_modules/issues
Platform: UNKNOWN
Classifier: Programming Language :: Python :: 3
Classifier: License :: OSI Approved :: MIT License
Classifier: Operating System :: OS Independent
Requires-Python: >=3.8
License-File: LICENSE.txt
